ersst5tools/__init__.py
ersst5tools/ersst5tools.py
ersst5tools/clims/dummy.py
ersst5tools/clims/sst_1886_1915.zarr/.zattrs
ersst5tools/clims/sst_1886_1915.zarr/.zgroup
ersst5tools/clims/sst_1886_1915.zarr/.zmetadata
ersst5tools/clims/sst_1886_1915.zarr/latitude/.zarray
ersst5tools/clims/sst_1886_1915.zarr/latitude/.zattrs
ersst5tools/clims/sst_1886_1915.zarr/latitude/0
ersst5tools/clims/sst_1886_1915.zarr/longitude/.zarray
ersst5tools/clims/sst_1886_1915.zarr/longitude/.zattrs
ersst5tools/clims/sst_1886_1915.zarr/longitude/0
ersst5tools/clims/sst_1886_1915.zarr/month/.zarray
ersst5tools/clims/sst_1886_1915.zarr/month/.zattrs
ersst5tools/clims/sst_1886_1915.zarr/month/0
ersst5tools/clims/sst_1886_1915.zarr/sst/.zarray
ersst5tools/clims/sst_1886_1915.zarr/sst/.zattrs
ersst5tools/clims/sst_1886_1915.zarr/sst/0.0.0
ersst5tools/clims/sst_1886_1915.zarr/sst/0.1.0
ersst5tools/clims/sst_1886_1915.zarr/sst/1.0.0
ersst5tools/clims/sst_1886_1915.zarr/sst/1.1.0
ersst5tools/clims/sst_1891_1920.zarr/.zattrs
ersst5tools/clims/sst_1891_1920.zarr/.zgroup
ersst5tools/clims/sst_1891_1920.zarr/.zmetadata
ersst5tools/clims/sst_1891_1920.zarr/latitude/.zarray
ersst5tools/clims/sst_1891_1920.zarr/latitude/.zattrs
ersst5tools/clims/sst_1891_1920.zarr/latitude/0
ersst5tools/clims/sst_1891_1920.zarr/longitude/.zarray
ersst5tools/clims/sst_1891_1920.zarr/longitude/.zattrs
ersst5tools/clims/sst_1891_1920.zarr/longitude/0
ersst5tools/clims/sst_1891_1920.zarr/month/.zarray
ersst5tools/clims/sst_1891_1920.zarr/month/.zattrs
ersst5tools/clims/sst_1891_1920.zarr/month/0
ersst5tools/clims/sst_1891_1920.zarr/sst/.zarray
ersst5tools/clims/sst_1891_1920.zarr/sst/.zattrs
ersst5tools/clims/sst_1891_1920.zarr/sst/0.0.0
ersst5tools/clims/sst_1891_1920.zarr/sst/0.1.0
ersst5tools/clims/sst_1891_1920.zarr/sst/1.0.0
ersst5tools/clims/sst_1891_1920.zarr/sst/1.1.0
ersst5tools/clims/sst_1896_1925.zarr/.zattrs
ersst5tools/clims/sst_1896_1925.zarr/.zgroup
ersst5tools/clims/sst_1896_1925.zarr/.zmetadata
ersst5tools-0.0.4.dist-info/METADATA
ersst5tools-0.0.4.dist-info/WHEEL
ersst5tools-0.0.4.dist-info/licenses/LICENSE
ersst5tools-0.0.4.dist-info/RECORD
