Metadata-Version: 2.3
Name: ersst5tools
Version: 0.0.4
Summary: Tools for processing ERSSTv5 data
Project-URL: Homepage, https://github.com/MutaharChalmers/ersst5tools
Author-email: Mutahar Chalmers <mutahar.chalmers@gmail.com>
License: MIT License
License-File: LICENSE
Classifier: Development Status :: 4 - Beta
Classifier: Intended Audience :: Science/Research
Classifier: License :: OSI Approved :: MIT License
Classifier: Operating System :: OS Independent
Classifier: Programming Language :: Python :: 3
Classifier: Topic :: Scientific/Engineering
Requires-Python: >=3.8
Requires-Dist: climperiods>=0.0.2
Requires-Dist: numpy>=1.18
Requires-Dist: scipy>=1.10
Requires-Dist: xarray>=2023.01.0
Requires-Dist: zarr>=2.18
